[
  {
    "job_title": "Software Engineering Intern",
    "title": "Software Engineering Intern",
    "employer_name": "Mechanize",
    "company_name": "Mechanize",
    "job_city": "San Francisco",
    "job_state": "CA",
    "job_country": "US",
    "job_description": "As a software engineering intern, you will assist the team in creating RL environments to sell to the leading AI labs. You might be a good fit if you are can write in python and you're highly intelligent. No prior machine learning or AI experience is required.",
    "job_apply_link": "https://jobs.ashbyhq.com/mechanize/d148d54f-6db7-4c28-9699-0304596f554e",
    "url": "https://jobs.ashbyhq.com/mechanize/d148d54f-6db7-4c28-9699-0304596f554e",
    "job_posted_at_datetime_utc": "2025-11-20T16:48:29.000Z",
    "job_employment_type": "INTERN",
    "terms": [
      "Summer 2026"
    ],
    "locations": [
      "San Francisco, CA"
    ],
    "category": "Software Engineering",
    "is_visible": true,
    "id": "jobs-ashbyhq-com-mechanize-d148d54f-6db7-4c28-9699-0304596f554e",
    "description_platform": "ashby",
    "description_success": true
  },
  {
    "job_title": "Software Application Developer Intern for GOES-R Series Satellites",
    "title": "Software Application Developer Intern for GOES-R Series Satellites",
    "employer_name": "KBR",
    "company_name": "KBR",
    "job_city": "Silver Spring",
    "job_state": "MD",
    "job_country": "US",
    "job_description": "Title:Software Application Developer Intern for GOES-R Series SatellitesBelong. Connect. Grow. with KBR! Around here, we define the future. We are a company of innovators, thinkers, creators, explorers, volunteers, and dreamers. But we all share one goal: to improve the world responsibly and safely by supporting the science that informs decision makers and protects Earth.About the InternshipJoin our 12-week immersive program supporting the future of environmental monitoring and prediction through the NOAA GOES-R Series of geostationary weather satellites. As a Student Mission Application Developer, you’ll work alongside experts across the NOAA/NWS weather enterprise, contributing to the development, integration, and deployment of software that processes, distributes, visualizes, and monitors satellite imagery and environmental observations.This role is designed for students who want to apply their programming skills to real-world weather, climate, ocean, and space-weather applications that protect lives and property and enable more accurate forecasting and situational awareness for the National Weather Service.The preferred duty location is NOAA/NWS Headquarters in Silver Spring, MD, with the possibility of remote participation for well-qualified candidates who can work independently.Your ImpactSupport and enhance operational weather and satellite-processing systems that power NOAA mission softwareContribute to visualization interfaces and environmental data tools used by NOAA scientists, NWS forecasters, and partners across the weather enterpriseParticipate in software testing and refinement for pre-operational and operational satellite productsCollaborate with specialists supporting one of NOAA’s flagship missions for the Nation’s weather-ready infrastructureGain hands-on experience at the intersection of software engineering, meteorology, Earth science, and satellite remote sensingMany past interns have contributed directly to operational NOAA/NWS systems, with several moving into full-time roles after graduation.Who Should ApplyWe’re seeking curious and motivated rising sophomores, juniors, seniors, or graduate students with combined strengths in computer science/engineering AND meteorology, atmospheric science, physical sciences, or Earth/space science.Ideal candidates are eager to work in the NOAA/NWS operational environment—bridging software, data, systems engineering, and applied science in ways that directly support forecasting, environmental intelligence, and hazard monitoring.If you’re passionate about applying technology to enhance weather forecasting, climate monitoring, satellite analysis, and environmental decision support, we want to hear from you.Required QualificationsHigh school diploma or equivalentEnrollment in an accredited undergraduate or graduate programStrong foundation in mathematics and geometry, including basic integral calculusTwo semesters of college physicsProficiency in Python, including object-oriented programming and scientific libraries (NumPy, SciPy)Functional experience with Linux environments (RedHat/CentOS), bash, and standard text editors (vi)Familiarity with Git version control workflowsPreferred SkillsExperience or interest in the NOAA, NWS, or U.S. weather enterprise, including exposure to satellite, radar, numerical weather prediction, or environmental data workflowsFamiliarity with Agile or Scrum software development practicesBasic knowledge of SQL or NoSQL databasesUnderstanding of scientific software development and practices for maintaining robust, scalable codeExposure to cloud-based environments used for data processing or scientific computingInterest in remote sensing, satellite products, AWIPS, environmental intelligence tools, or forecasting workflowsStrong problem-solving and debugging skillsExcellent communication skills, with an ability to translate technical concepts for scientists, engineers, and operational usersEagerness to explore new tools, technologies, and methodologies used across the weather enterpriseOptional Focus Areas Depending on your academic background and project assignments, you may work on:Scientific visualization using JavaScript (e.g., D3.js)Satellite imagery processing, feature extraction, or algorithm prototypingData science techniques for user analytics, monitoring, and system diagnosticsEnhancing tools commonly used by NWS forecasters and NOAA scientistsWhat We OfferMentorship: Personalized guidance from experienced engineers and scientistsMeaningful Work: Contribute to NOAA systems with real-world national impactProfessional Development: Build technical, analytical, and leadership skillsPathways to Full-Time Roles: Many of our interns go on to join KBR or our partner organizations in full-time positionsInclusive Culture: We believe that diverse teams build better solutions, and we encourage applicants from all backgrounds to applyCompensation$45,600 – $68,300/year equivalentFinal rate determined by location, qualifications, and schedule. Hourly pay will be adjusted for part-time or full-time availability.EligibilityU.S. Citizenship is required due to the nature of the workWe believe in building a diverse and inclusive workplace—we welcome applicants of all backgrounds, experiences, and perspectivesLearn MoreAbout the GOES-R Series Mission: https://www.goes-r.govReady to launch your career and contribute to a mission that matters? Apply todayKBR Benefits​KBR offers a selection of competitive lifestyle benefits which could include 401K plan with company match, medical, dental, vision, life insurance, AD&D, flexible spending account, disability, paid time off, or flexible work schedule. We support career advancement through professional training and development.​Click here to learn more: KBR Benefits#LI-EM2Belong, Connect and Grow at KBRAt KBR, we are passionate about our people and our Zero Harm culture. These inform all that we do and are at the heart of our commitment to, and ongoing journey toward being a People First company. That commitment is central to our team of team’s philosophy and fosters an environment where everyone can Belong, Connect and Grow. We Deliver – Together. KBR is an equal opportunity employer. All qualified applicants will receive consideration for employment without regard to race, color, religion, disability, sex, sexual orientation, gender identity or expression, age, national origin, veteran status, genetic information, union status and/or beliefs, or any other characteristic protected by federal, state, or local law.",
    "job_apply_link": "https://kbr.wd5.myworkdayjobs.com/en-US/KBR_Careers/job/Silver-Spring-Maryland/Software-Application-Developer-Intern-for-GOES-R-Series-Satellites_R2115543",
    "url": "https://kbr.wd5.myworkdayjobs.com/en-US/KBR_Careers/job/Silver-Spring-Maryland/Software-Application-Developer-Intern-for-GOES-R-Series-Satellites_R2115543",
    "job_posted_at_datetime_utc": "2025-11-20T16:49:15.000Z",
    "job_employment_type": "INTERN",
    "terms": [
      "Summer 2026"
    ],
    "locations": [
      "Silver Spring, MD"
    ],
    "category": "Software Engineering",
    "is_visible": true,
    "id": "kbr-wd5-myworkdayjobs-com-en-us-kbr_careers-job-silver-spring-maryland-software-application-developer-intern-for-goes-r-series-satellites_r2115543",
    "description_platform": "workday",
    "description_success": true
  },
  {
    "job_title": "Intern Software Engineer",
    "title": "Intern Software Engineer",
    "employer_name": "General Dynamics Mission Systems",
    "company_name": "General Dynamics Mission Systems",
    "job_city": "Scottsdale",
    "job_state": "AZ",
    "job_country": "US",
    "job_description": "var useAutoScrolling = false; if (window.addEventListener) { window.addEventListener('message', icims_handlePostMessage, false); } else if (window.attachEvent) { window.attachEvent('onmessage', icims_handlePostMessage); } function icims_handlePostMessage(event) { // If this is not a message from an icims domain, ignore it. if (event.origin.indexOf('icims.com') == -1) return; var data = event.data; if (typeof data === \"string\") { try { data = ICIMS.jsonDecode(data); } catch(e) { data = event.data; } } try { if (data && data.height && !isNaN(data.height)) { document.getElementById('icims_content_iframe').height = parseInt(data.height); } else if ((data && 'x' in data && 'y' in data && !isNaN(parseInt(data.x)) && !isNaN(parseInt(data.y)))) { top.scrollTo(parseInt(data.x), parseInt(data.y)); } else if(data && data.pageTitle){ window.document.title = data.pageTitle; } } catch (e) {} } function getCookie(name) { var match = document.cookie.match(name + '=(.*?)(;|$)'); if (match) return unescape(match[1]); else return \"\"; } function updateUrl(url) { try { history.replaceState({}, '', url); } catch (e) {} } icimsAddOnload(function() { var icimsFrame = document.createElement('iframe'); var iFrameHeight = 500; icimsFrame.id = 'icims_content_iframe'; icimsFrame.name = 'icims_content_iframe'; icimsFrame.src = 'https:\\/\\/careers-gdms.icims.com\\/jobs\\/68290\\/intern-software-engineer\\/job?in_iframe=1'; icimsFrame.setAttribute('style', 'width: 100%;border: none;margin: 0px'); iFrameHeight = 500; icimsFrame.setAttribute('height', iFrameHeight); icimsFrame.setAttribute('title', 'iCIMS Content iFrame'); icimsFrame.onload=function() { try { window.parent.parent.scrollTo(0,0); } catch (e) {} }; document.getElementById('icims_iframe_span').appendChild(icimsFrame); try { var height = getCookie('cookie_icims_iframe_content_height'); if (height > 0 && typeof style !== 'undefined') style.height = height + 'px'; } catch(e) {} document.getElementById('icims_content_iframe').onreadystatechange = function() { try{ if ('interactive' == this.readyState) { window.scroll(1,1); } } catch(e) {} }; try { var height = 0; if (navigator.userAgent.indexOf(\"Firefox\")!=-1) height = document.body.offsetHeight + 16; else height = document.body.scrollHeight; document.cookie=\"cookie_icims_iframe_content_height=\"+height+\";SameSite=Strict;Secure;path=/;\"; } catch(e) {} }); <iframe src=\"https://careers-gdms.icims.com/jobs/68290/intern-software-engineer/job?in_iframe=1\" id=\"noscript_icims_content_iframe\" name=\"noscript_icims_content_iframe\" title=\"Noscript iCIMS Content iFrame\" style=\"width:100%;\" height=\"500\"></iframe>",
    "job_apply_link": "https://careers-gdms.icims.com/jobs/68290/intern-software-engineer/job",
    "url": "https://careers-gdms.icims.com/jobs/68290/intern-software-engineer/job",
    "job_posted_at_datetime_utc": "2025-11-20T16:50:14.000Z",
    "job_employment_type": "INTERN",
    "terms": [
      "Summer 2026"
    ],
    "locations": [
      "Scottsdale, AZ"
    ],
    "category": "Software Engineering",
    "is_visible": true,
    "id": "careers-gdms-icims-com-jobs-68290-intern-software-engineer-job",
    "description_platform": "icims",
    "description_success": true
  },
  {
    "job_title": "Software Intern Engineer - Tactical Radios",
    "title": "Software Intern Engineer - Tactical Radios",
    "employer_name": "General Dynamics Mission Systems",
    "company_name": "General Dynamics Mission Systems",
    "job_city": "Scottsdale",
    "job_state": "AZ",
    "job_country": "US",
    "job_description": "var useAutoScrolling = false; if (window.addEventListener) { window.addEventListener('message', icims_handlePostMessage, false); } else if (window.attachEvent) { window.attachEvent('onmessage', icims_handlePostMessage); } function icims_handlePostMessage(event) { // If this is not a message from an icims domain, ignore it. if (event.origin.indexOf('icims.com') == -1) return; var data = event.data; if (typeof data === \"string\") { try { data = ICIMS.jsonDecode(data); } catch(e) { data = event.data; } } try { if (data && data.height && !isNaN(data.height)) { document.getElementById('icims_content_iframe').height = parseInt(data.height); } else if ((data && 'x' in data && 'y' in data && !isNaN(parseInt(data.x)) && !isNaN(parseInt(data.y)))) { top.scrollTo(parseInt(data.x), parseInt(data.y)); } else if(data && data.pageTitle){ window.document.title = data.pageTitle; } } catch (e) {} } function getCookie(name) { var match = document.cookie.match(name + '=(.*?)(;|$)'); if (match) return unescape(match[1]); else return \"\"; } function updateUrl(url) { try { history.replaceState({}, '', url); } catch (e) {} } icimsAddOnload(function() { var icimsFrame = document.createElement('iframe'); var iFrameHeight = 500; icimsFrame.id = 'icims_content_iframe'; icimsFrame.name = 'icims_content_iframe'; icimsFrame.src = 'https:\\/\\/careers-gdms.icims.com\\/jobs\\/68798\\/software-intern-engineer---tactical-radios\\/job?in_iframe=1'; icimsFrame.setAttribute('style', 'width: 100%;border: none;margin: 0px'); iFrameHeight = 500; icimsFrame.setAttribute('height', iFrameHeight); icimsFrame.setAttribute('title', 'iCIMS Content iFrame'); icimsFrame.onload=function() { try { window.parent.parent.scrollTo(0,0); } catch (e) {} }; document.getElementById('icims_iframe_span').appendChild(icimsFrame); try { var height = getCookie('cookie_icims_iframe_content_height'); if (height > 0 && typeof style !== 'undefined') style.height = height + 'px'; } catch(e) {} document.getElementById('icims_content_iframe').onreadystatechange = function() { try{ if ('interactive' == this.readyState) { window.scroll(1,1); } } catch(e) {} }; try { var height = 0; if (navigator.userAgent.indexOf(\"Firefox\")!=-1) height = document.body.offsetHeight + 16; else height = document.body.scrollHeight; document.cookie=\"cookie_icims_iframe_content_height=\"+height+\";SameSite=Strict;Secure;path=/;\"; } catch(e) {} }); <iframe src=\"https://careers-gdms.icims.com/jobs/68798/software-intern-engineer---tactical-radios/job?in_iframe=1\" id=\"noscript_icims_content_iframe\" name=\"noscript_icims_content_iframe\" title=\"Noscript iCIMS Content iFrame\" style=\"width:100%;\" height=\"500\"></iframe>",
    "job_apply_link": "https://careers-gdms.icims.com/jobs/68798/software-intern-engineer---tactical-radios/job",
    "url": "https://careers-gdms.icims.com/jobs/68798/software-intern-engineer---tactical-radios/job",
    "job_posted_at_datetime_utc": "2025-11-20T16:52:00.000Z",
    "job_employment_type": "INTERN",
    "terms": [
      "Summer 2026"
    ],
    "locations": [
      "Scottsdale, AZ"
    ],
    "category": "Software Engineering",
    "is_visible": true,
    "id": "careers-gdms-icims-com-jobs-68798-software-intern-engineer-tactical-radios-job",
    "description_platform": "icims",
    "description_success": true
  },
  {
    "job_title": "Site Reliability Software Engineer Intern",
    "title": "Site Reliability Software Engineer Intern",
    "employer_name": "DocuSign",
    "company_name": "DocuSign",
    "job_city": "Seattle",
    "job_state": "WA",
    "job_country": "US",
    "job_description": "Back to Docusign.com Toggle navigation var snapIcon = document.querySelector('#snap-left'); if (snapIcon) { snapIcon.addEventListener('click', function() { document.querySelector('#header-nav--collapse').classList.toggle('expanded'); }); var w = window.innerWidth; var h = window.innerHeight; window.addEventListener('resize', function() { /* Check that width has actual changed. This is a fix to mobile scroll which can trigger resize event*/ if (window.innerWidth !== w && window.innerHeight !== h) { //reset width and height we check with. w = window.innerWidth; h = window.innerHeight; if (document.querySelector('#header-nav--collapse').classList.contains('expanded')) { document.querySelector('#header-nav--collapse').classList.remove('expanded'); } } }); } Overview Jobs Benefits Culture DE&I Students Sustainability Search jobs Sign In Join our talent community Sign in to view your application status United States Canada EMEA LATAM APAC India Join our talent community Sign in View your application status United States Canada EMEA LATAM APAC India Search jobs var useAutoScrolling = false; if (window.addEventListener) { window.addEventListener('message', icims_handlePostMessage, false); } else if (window.attachEvent) { window.attachEvent('onmessage', icims_handlePostMessage); } function icims_handlePostMessage(event) { // If this is not a message from an icims domain, ignore it. if (event.origin.indexOf('icims.com') == -1) return; var data = event.data; if (typeof data === \"string\") { try { data = ICIMS.jsonDecode(data); } catch(e) { data = event.data; } } try { if (data && data.height && !isNaN(data.height)) { document.getElementById('icims_content_iframe').height = parseInt(data.height); } else if ((data && 'x' in data && 'y' in data && !isNaN(parseInt(data.x)) && !isNaN(parseInt(data.y)))) { top.scrollTo(parseInt(data.x), parseInt(data.y)); } else if(data && data.pageTitle){ window.document.title = data.pageTitle; } } catch (e) {} } function getCookie(name) { var match = document.cookie.match(name + '=(.*?)(;|$)'); if (match) return unescape(match[1]); else return \"\"; } function updateUrl(url) { try { history.replaceState({}, '', url); } catch (e) {} } icimsAddOnload(function() { var icimsFrame = document.createElement('iframe'); var iFrameHeight = 500; icimsFrame.id = 'icims_content_iframe'; icimsFrame.name = 'icims_content_iframe'; icimsFrame.src = 'https:\\/\\/uscareers-docusign.icims.com\\/jobs\\/28219\\/site-reliability-software-engineer-intern\\/job?in_iframe=1'; icimsFrame.setAttribute('style', 'width: 100%;border: none;margin: 0px'); iFrameHeight = 500; icimsFrame.setAttribute('height', iFrameHeight); icimsFrame.setAttribute('title', 'iCIMS Content iFrame'); icimsFrame.onload=function() { try { window.parent.parent.scrollTo(0,0); } catch (e) {} }; document.getElementById('icims_iframe_span').appendChild(icimsFrame); try { var height = getCookie('cookie_icims_iframe_content_height'); if (height > 0 && typeof style !== 'undefined') style.height = height + 'px'; } catch(e) {} document.getElementById('icims_content_iframe').onreadystatechange = function() { try{ if ('interactive' == this.readyState) { window.scroll(1,1); } } catch(e) {} }; try { var height = 0; if (navigator.userAgent.indexOf(\"Firefox\")!=-1) height = document.body.offsetHeight + 16; else height = document.body.scrollHeight; document.cookie=\"cookie_icims_iframe_content_height=\"+height+\";SameSite=Strict;Secure;path=/;\"; } catch(e) {} }); <iframe src=\"https://uscareers-docusign.icims.com/jobs/28219/site-reliability-software-engineer-intern/job?in_iframe=1\" id=\"noscript_icims_content_iframe\" name=\"noscript_icims_content_iframe\" title=\"Noscript iCIMS Content iFrame\" style=\"width:100%;\" height=\"500\"></iframe> Nav.renderStaticFooter('footer'); window.addEventListener('DOMContentLoaded', function(){ const workFromHome = document.querySelector(\".similar-jobs-container .job-caption-container #job-wfh\").parentNode; workFromHome.style.display = \"none\"; }) document.addEventListener(\"DOMContentLoaded\", function () { const jdBtn = document.getElementById(\"social-share\"); const jdCTA = `<a href=\"https://www.docusign.com/privacy/applicant-candidate-notice\" target=\"_blank\" class=\"apply __button btn-primary jd-privacy-notice-cta\">Applicant and Candidate Privacy Notice</a>`; jdBtn.insertAdjacentHTML('beforeend', jdCTA); });",
    "job_apply_link": "https://uscareers-docusign.icims.com/jobs/28219/site-reliability-software-engineer-intern/job",
    "url": "https://uscareers-docusign.icims.com/jobs/28219/site-reliability-software-engineer-intern/job",
    "job_posted_at_datetime_utc": "2025-11-20T16:52:38.000Z",
    "job_employment_type": "INTERN",
    "terms": [
      "Summer 2026"
    ],
    "locations": [
      "Seattle, WA"
    ],
    "category": "Software Engineering",
    "is_visible": true,
    "id": "uscareers-docusign-icims-com-jobs-28219-site-reliability-software-engineer-intern-job",
    "description_platform": "icims",
    "description_success": true
  }
]